idea_extractor/__init__.py
idea_extractor/main.py
idea_extractor/prompts.py
idea_extractor-2025.12.21195340.dist-info/METADATA
idea_extractor-2025.12.21195340.dist-info/WHEEL
idea_extractor-2025.12.21195340.dist-info/top_level.txt
idea_extractor-2025.12.21195340.dist-info/RECORD
