Metadata-Version: 2.4
Name: idea-extractor
Version: 2025.12.21195340
Summary: idea-extractor extracts, categorizes, and scores high‑impact software ideas from forum discussions, outputting themes, feasibility and market impact.
Author-email: idea-extractor <hi@eugene.plus>
License: MIT
Project-URL: Homepage, https://github.com/chigwell/idea-extractor
Requires-Python: >=3.9
Requires-Dist: langchain-llm7>=0.0.0
Requires-Dist: llmatch-messages>=0.0.0
Requires-Dist: langchain-core>=0.3.0
